dryftseeker/__init__.py
dryftseeker/dryftseeker.cpython-310-linux.so
dryftseeker/dryftseeker.cpython-311-linux.so
dryftseeker/dryftseeker.cpython-38-linux.so
dryftseeker/dryftseeker.cpython-39-linux.so
dryftseeker/dryftseeker.py
dryftseeker/bin/coll-linux
dryftseeker/scripts/seekeragg.sh
dryftseeker-0.0.10.dist-info/AUTHORS.rst
dryftseeker-0.0.10.dist-info/LICENSE.rst
dryftseeker-0.0.10.dist-info/METADATA
dryftseeker-0.0.10.dist-info/WHEEL
dryftseeker-0.0.10.dist-info/top_level.txt
dryftseeker-0.0.10.dist-info/RECORD
